el/__init__.py
el/analysis.py
el/async_tools.py
el/callback_manager.py
el/containers.py
el/errors.py
el/history_manager.py
el/lifetime.py
el/nixos_ctk_font_fix.py
el/numbers.py
el/terminal.py
el/time_utils.py
el/timers.py
el/typing_tools.py
el/assets/__init__.py
el/assets/_deps.py
el/assets/_manager.py
el/assets/builtin/backspace.png
el/assets/builtin/cancel.png
el/assets/builtin/enter.png
el/bindantic/__init__.py
el/bindantic/_base_struct.py
el/bindantic/_config.py
el/bindantic/_deps.py
el/bindantic/_fields.py
el/bindantic/_struct_construction.py
el/ctk_utils/__init__.py
el/ctk_utils/_colors.py
el/ctk_utils/_deps.py
el/ctk_utils/_dynamic_config.py
el/ctk_utils/_scaling.py
el/ctk_utils/types.py
el/datastore/__init__.py
el/datastore/_deps.py
el/datastore/_file.py
el/datastore/_savable.py
el/datastore/_specialized.py
el/datastore/_versioning.py
el/mpl_utils/__init__.py
el/mpl_utils/_deps.py
el/mpl_utils/_dragging_manager.py
el/mpl_utils/_transforms.py
el/observable/__init__.py
el/observable/_composed.py
el/observable/_observable.py
el/observable/filters.py
el/tkml/__init__.py
el/tkml/_context.py
el/tkml/_deps.py
el/tkml/adapters.py
el/tkml/grid.py
el/tkml/pack.py
el/widgets/__init__.py
el/widgets/_defaults.py
el/widgets/_deps.py
el/widgets/keyboard.py
el/widgets/listbox.py
el/widgets/spinbox.py
el/widgets/toolbar_button.py
el/widgets/tooltip.py
el/widgets/value_box.py
el/widgets/ctkex/__init__.py
el/widgets/ctkex/_button_ex.py
el/widgets/ctkex/_combo_box_ex.py
el/widgets/ctkex/_entry_ex.py
el/widgets/ctkex/_frame_ex.py
el/widgets/ctkex/_scrollable_frame_ex.py
el/widgets/ctkex/_segmented_button_ex.py
el/widgets/ctkex/_switch_ex.py
el_std_py-0.4.0.dist-info/licenses/LICENSE
el_std_py-0.4.0.dist-info/METADATA
el_std_py-0.4.0.dist-info/WHEEL
el_std_py-0.4.0.dist-info/top_level.txt
el_std_py-0.4.0.dist-info/RECORD
