Metadata-Version: 2.4
Name: el-std-py
Version: 0.4.0
Summary: An assortment of useful python utilities complementing some builtin and third party python packages
Author-email: melektron <matteo@elektron.work>
Project-URL: Homepage, https://github.com/melektron/el_std_py
Project-URL: Issues, https://github.com/melektron/el_std_py/issues
Classifier: Programming Language :: Python :: 3.13
Classifier: License :: OSI Approved :: Apache Software License
Classifier: Operating System :: OS Independent
Requires-Python: >=3.12
License-File: LICENSE
Dynamic: license-file
